mc_migrate/__init__.py
mc_migrate/mcmigrate.py
mc_migrate-0.1.0a0.dist-info/LICENSE.ISC
mc_migrate-0.1.0a0.dist-info/METADATA
mc_migrate-0.1.0a0.dist-info/WHEEL
mc_migrate-0.1.0a0.dist-info/entry_points.txt
mc_migrate-0.1.0a0.dist-info/RECORD
